README.md
setup.py
aioetcd/__init__.py
aioetcd/client.py
aioetcd.egg-info/PKG-INFO
aioetcd.egg-info/SOURCES.txt
aioetcd.egg-info/dependency_links.txt
aioetcd.egg-info/requires.txt
aioetcd.egg-info/top_level.txt
aioetcd.egg-info/zip-safe